[
  { "id": 1, "name": "Urban Casual Shirt", "price": 899, "category": "Men", "img": "/images/men/m1.jpg" },
  { "id": 2, "name": "Premium Cotton Tee", "price": 499, "category": "Men", "img": "/images/men/m2.jpg" },
  { "id": 3, "name": "Rugged Denim Jeans", "price": 1299, "category": "Men", "img": "/images/men/m3.jpg" },
  { "id": 4, "name": "Executive Formal Suit", "price": 1899, "category": "Men", "img": "/images/men/m4.jpg" },
  { "id": 5, "name": "Royal Ethnic Kurta", "price": 2499, "category": "Men", "img": "/images/men/m5.jpg" },
  { "id": 6, "name": "Celebration Blazer", "price": 3500, "category": "Men", "img": "/images/men/m6.jpg" },

  { "id": 7, "name": "Graceful Silk Saree", "price": 2500, "category": "Women", "img": "/images/women/w1.jpg" },
  { "id": 8, "name": "Designer Kurti Set", "price": 1200, "category": "Women", "img": "/images/women/w2.jpg" },
  { "id": 9, "name": "Modern Midi Dress", "price": 1500, "category": "Women", "img": "/images/women/w3.jpg" },
  { "id": 10, "name": "Chic Fashion Top", "price": 699, "category": "Women", "img": "/images/women/w4.jpg" },
  { "id": 11, "name": "Slim Fit Trousers", "price": 999, "category": "Women", "img": "/images/women/w5.jpg" },
  { "id": 12, "name": "Elegant Party Gown", "price": 4500, "category": "Women", "img": "/images/women/w6.jpg" },

  { "id": 13, "name": "Kids Trendy Tee", "price": 399, "category": "Kids", "img": "/images/kids/k1.jpg" },
  { "id": 14, "name": "Active Denim Shorts", "price": 799, "category": "Kids", "img": "/images/kids/k2.jpg" },
  { "id": 15, "name": "Princess Party Frock", "price": 999, "category": "Kids", "img": "/images/kids/k3.jpg" },
  { "id": 16, "name": "Kids Festive Wear", "price": 1499, "category": "Kids", "img": "/images/kids/k4.jpg" },
  { "id": 17, "name": "Warm Winter Hoodie", "price": 1200, "category": "Kids", "img": "/images/kids/k5.jpg" },
  { "id": 18, "name": "Comfy Night Set", "price": 599, "category": "Kids", "img": "/images/kids/k6.jpg" },

  { "id": 19, "name": "Soft Baby Romper", "price": 450, "category": "Newborn", "img": "/images/newborn/n1.jpg" },
  { "id": 20, "name": "Cute Baby Onesie", "price": 350, "category": "Newborn", "img": "/images/newborn/n2.jpg" },
  { "id": 21, "name": "Cradle Dress Set", "price": 899, "category": "Newborn", "img": "/images/newborn/n3.jpg" },
  { "id": 22, "name": "Tiny Socks & Mittens", "price": 199, "category": "Newborn", "img": "/images/newborn/n4.jpg" },
  { "id": 23, "name": "Soft Baby Blanket", "price": 699, "category": "Newborn", "img": "/images/newborn/n5.jpg" },
  { "id": 24, "name": "Sweet Baby Cap", "price": 150, "category": "Newborn", "img": "/images/newborn/n6.jpg" }
]